torchcoach/loggers/base.py
torchcoach/loggers/display.py
torchcoach/loggers/tensorboard.py
torchcoach-0.1.0.dist-info/LICENSE
torchcoach-0.1.0.dist-info/WHEEL
torchcoach-0.1.0.dist-info/METADATA
torchcoach-0.1.0.dist-info/RECORD
