Metadata-Version: 2.1
Name: torchcoach
Version: 0.1.0
Summary: A project aiming at simplifying training of PyTorch models and provide support for the continual learning setting.
Author: Reza Davari
Author-email: rezazzr@hotmail.com
Requires-Python: >=3.8,<4.0
Classifier: Programming Language :: Python :: 3
Classifier: Programming Language :: Python :: 3.8
Classifier: Programming Language :: Python :: 3.9
Requires-Dist: aiohttp (>=3.8.1,<4.0.0)
Requires-Dist: aiohttp_cors (>=0.7.0,<0.8.0)
Requires-Dist: black (>=22.3.0,<23.0.0)
Requires-Dist: jupyter (>=1.0.0,<2.0.0)
Requires-Dist: numpy (>=1.22.3,<2.0.0)
Requires-Dist: pandas (>=1.4.2,<2.0.0)
Requires-Dist: prettytable (>=3.2.0,<4.0.0)
Requires-Dist: tensorboard (>=2.8.0,<3.0.0)
Requires-Dist: torch (>=1.11.0,<2.0.0)
Requires-Dist: tqdm (>=4.64.0,<5.0.0)
